openaudit/__init__.py
openaudit/__main__.py
openaudit/main.py
openaudit/ai/__init__.py
openaudit/ai/engine.py
openaudit/ai/ethics.py
openaudit/ai/models.py
openaudit/ai/protocol.py
openaudit/core/__init__.py
openaudit/core/config.py
openaudit/core/domain.py
openaudit/core/ignore_manager.py
openaudit/core/interfaces.py
openaudit/core/rules_engine.py
openaudit/features/__init__.py
openaudit/features/architecture/__init__.py
openaudit/features/architecture/agent.py
openaudit/features/architecture/models.py
openaudit/features/architecture/scanner.py
openaudit/features/config/__init__.py
openaudit/features/config/scanner.py
openaudit/features/dataflow/__init__.py
openaudit/features/dataflow/agent.py
openaudit/features/dataflow/models.py
openaudit/features/dataflow/scanner.py
openaudit/features/explain/__init__.py
openaudit/features/explain/agent.py
openaudit/features/secrets/__init__.py
openaudit/features/secrets/agent.py
openaudit/features/secrets/context.py
openaudit/features/secrets/scanner.py
openaudit/features/threat_model/__init__.py
openaudit/features/threat_model/agent.py
openaudit/interface/__init__.py
openaudit/interface/cli/__init__.py
openaudit/interface/cli/app.py
openaudit/interface/cli/commands.py
openaudit/interface/cli/ui.py
openaudit/reporters/base.py
openaudit/reporters/console.py
openaudit/reporters/json_reporter.py
openaudit/rules/config.yaml
openaudit/rules/secrets.yaml
openaudit-0.1.1.dist-info/licenses/LICENSE
openaudit-0.1.1.dist-info/METADATA
openaudit-0.1.1.dist-info/WHEEL
openaudit-0.1.1.dist-info/entry_points.txt
openaudit-0.1.1.dist-info/top_level.txt
openaudit-0.1.1.dist-info/RECORD
