Metadata-Version: 2.4
Name: openaudit
Version: 0.1.1
Summary: Offline-first security audit tool (secrets & config scanning) for local codebases.
Author-email: OpenAuditKit Team <info@neuralforge.one>
License: MIT
Project-URL: Repository, https://github.com/neuralforgeone/OpenAuditKit
Project-URL: Issues, https://github.com/neuralforgeone/OpenAuditKit/issues
Classifier: Programming Language :: Python :: 3
Classifier: License :: OSI Approved :: MIT License
Classifier: Operating System :: OS Independent
Requires-Python: >=3.9
License-File: LICENSE
Requires-Dist: typer>=0.9.0
Requires-Dist: pyyaml>=6.0
Requires-Dist: rich>=13.0.0
Requires-Dist: pydantic>=2.0.0
Requires-Dist: pathspec>=0.11.0
Requires-Dist: openai>=1.0.0
Provides-Extra: dev
Requires-Dist: pytest>=7.0.0; extra == "dev"
Requires-Dist: pytest-cov>=4.0.0; extra == "dev"
Dynamic: license-file
